easyxl/__init__.py
easyxl/__main__.py
easyxl/excel2json.py
easyxl/utils.py
easyxl-1.0.18.dist-info/LICENSE
easyxl-1.0.18.dist-info/METADATA
easyxl-1.0.18.dist-info/WHEEL
easyxl-1.0.18.dist-info/top_level.txt
easyxl-1.0.18.dist-info/RECORD
