Metadata-Version: 2.1
Name: easyxl
Version: 1.0.18
Summary: UNKNOWN
Home-page: https://github.com/leeheisen/easyxl
Author: leeheisen
License: UNKNOWN
Platform: UNKNOWN
Classifier: Programming Language :: Python :: 3
Classifier: License :: OSI Approved :: MIT License
Classifier: Operating System :: OS Independent
Requires-Python: >=3.10
Requires-Dist: xlwings
Requires-Dist: mjson5
